Workbook

Sheet 1_RBI_Data
A1: Regulation Area | B1: Status
A2: Digital Lending Guidelines | B2: Applicable
A3: KFS Required | B3: Yes
A4: APR Disclosure | B4: Mandatory
A5: Cooling Off Period | B5: Mandatory
A6: Direct Borrower-Lender Flow | B6: Required
A7: LSP Fund Handling | B7: Not Allowed
A8: Recovery Agent Disclosure | B8: Required
A9: Grievance Officer | B9: Required
A10: Data Privacy Compliance | B10: Required
A11: RBI Regulated Entity Needed | B11: Yes

Sheet 2_UPI_Data
A1: Month | B1: No. of Banks live on UPI | C1: Volume (In Mn.) | D1: Value (In Cr.)
A2: April-2026 | B2: 713 | C2: 22346.8 | D2: 29,029,88.05

Sheet 3_Population
A1: Metric | B1: Value | C1: Source
A2: India Population (2025) | B2: 1429.4 M | C2: Statistics Times / Population Estimate
A3: Urban Population % | B3: 0.36 | C3: World Bank
A4: Internet Users % | B4: 0.55 | C4: World Bank / DataReportal
A5: Smartphone Users % | B5: 0.75 | C5: Industry Reports
A6: Target Age Group (22–38) % | B6: 0.3 | C6: Census-Based Estimate

Sheet 4_State_Data
A1: State | B1: Population_M
A2: Uttar Pradesh | B2: 243.5
A3: Bihar | B3: 132.9
A4: Maharashtra | B4: 129.6
A5: West Bengal | B5: 100.6
A6: Madhya Pradesh | B6: 90
A7: Rajasthan | B7: 83.9
A8: Tamil Nadu | B8: 77.6
A9: Gujarat | B9: 74.3
A10: Karnataka | B10: 69.1
A11: Andhra Pradesh | B11: 53.7

Sheet 5_Competitors
A1: Competitor | B1: Type | C1: Users_M | D1: Merchants | E1: Strength
A2: Simpl | B2: BNPL | C2: 12 | D2: 26000 | E2: Checkout UX
A3: LazyPay | B3: BNPL | C3: 10 | D3: 20000 | E3: Consumer Credit
A4: ZestMoney | B4: BNPL | C4: 17 | D4: 10000 | E4: EMI Financing
A5: Amazon Pay Later | B5: BNPL | C5: 20 | D5: 30000 | E5: Ecosystem
A6: Flipkart Pay Later | B6: BNPL | C6: 18 | D6: 50000 | E6: Marketplace
A7: Bajaj Finance | B7: EMI | C7: 88 | D7: 190000 | E7: Scale

Sheet 6_BNPL_Market
A1: Metric | B1: Value
A2: India Digital Lending Market ($B) | B2: 45
A3: BNPL Share % | B3: 18
A4: BNPL TAM ($B) | B4: 8.1
A5: CAGR % | B5: 28
A6: 2025 TAM ($B) | B6: 10.4
A7: 2026 TAM ($B) | B7: 13.3
A8: 2027 TAM ($B) | B8: 17

Sheet 7_Customer_Segments
A1: Segment | B1: Age | C1: Income | D1: Priority
A2: Students | B2: 18-24 | C2: <25k | D2: Medium
A3: Young Professionals | B3: 22-35 | C3: 25k-80k | D3: High
A4: Salaried Millennials | B4: 25-40 | C4: 40k-120k | D4: High
A5: Gig Workers | B5: 20-40 | C5: Variable | D5: Medium
A6: New-to-Credit Users | B6: 18-35 | C6: Any | D6: Very High

Sheet 8_Risks_Regulation
A1: Risk | B1: Impact | C1: Mitigation
A2: Credit Default | B2: High | C2: Credit Scoring
A3: Fraud | B3: High | C3: KYC + Device Checks
A4: RBI Regulation | B4: High | C4: Compliance Team
A5: Merchant Churn | B5: Medium | C5: Better Incentives
A6: Customer Acquisition Cost | B6: Medium | C6: Referral Programs
A7: Data Breach | B7: High | C7: Encryption
A8: Economic Slowdown | B8: Medium | C8: Conservative Lending

Sheet 9_Merchant_Segments
A1: Segment | B1: Priority
A2: Electronics | B2: Very High
A3: Fashion | B3: High
A4: Travel | B4: High
A5: Healthcare | B5: Medium
A6: Grocery | B6: Medium
A7: Food Delivery | B7: Medium
A8: Education | B8: Medium

Sheet 10_Unit_Economics
A1: Metric | B1: Value
A2: Avg Transaction ₹ | B2: 3500
A3: Transactions/User/Year | B3: 8
A4: MDR % | B4: 2.5
A5: Revenue/User/Year ₹ | B5: 700
A6: CAC ₹ | B6: 400
A7: Gross Margin % | B7: 65
A8: Default Rate % | B8: 3
A9: Contribution Margin ₹ | B9: 255

Sheet 11_Market_Sizing
A1: India Digital Lending Market ($B) | B1: $45.0B
A2: BNPL Share (%) | B2: 0.18
A3: BNPL TAM ($B) | B3: =45*18% -> 8.1
A4: CAGR (%) | B4: 0.28
A5: Year | B5: TAM ($B)
A6: 2024 TAM ($B) | B6: 8.1
A7: 2025 TAM ($B) | B7: 10.37
A8: 2026 TAM ($B) | B8: 13.27
A9: 2027 TAM ($B) | B9: 16.99
A11: Metric | B11: Customers (M)
A12: Urban Population (M) | B12: 514
A13: Target Age Group | B13: =B12*30% -> 154.2
A14: Smartphone Users | B14: =B13*75% -> 115.65
A15: Income Match | B15: =B14*40% -> 46.26
A17: Addressable Customers (M) | B17: =B15 -> 46.26
A18: Revenue/User (₹) | B18: 700
A19: Bottom-Up TAM (₹ Cr) | B19: =(B17*B18)/10 -> 3238.2
A20: Year 5 SOM Revenue ($B) | B20: 1.13
A22: Year | B22: SOM Share | C22: Revenue ($M)
A23: 1 | B23: 0.005 | C23: =$B$3*1000*B23 -> 40.5
A24: 2 | B24: 0.015 | C24: =$B$3*1000*B24 -> 121.5
A25: 3 | B25: 0.04 | C25: =$B$3*1000*B25 -> 324
A26: 4 | B26: 0.08 | C26: =$B$3*1000*B26 -> 648
A27: 5 | B27: 0.14 | C27: =$B$3*1000*B27 -> 1134

Sheet 12_Financial_Model
A1: Year | B1: Users | C1: Revenue/User | D1: Revenue Cr
A2: 2025 | B2: 100000 | C2: 700 | D2: =(B2*C2)/10000000 -> 7
A3: 2026 | B3: 300000 | C3: 700 | D3: =(B3*C3)/10000000 -> 21
A4: 2027 | B4: 800000 | C4: 700 | D4: =(B4*C4)/10000000 -> 56
A5: 2028 | B5: 1500000 | C5: 700 | D5: =(B5*C5)/10000000 -> 105
A6: 2029 | B6: 2500000 | C6: 700 | D6: =(B6*C6)/10000000 -> 175
A8: Year | B8: Users | C8: CAC ₹ | D8: Acquisition Cost Cr
A9: 2025 | B9: 100000 | C9: 400 | D9: =(B9*C9)/10000000 -> 4
A10: 2026 | B10: 300000 | C10: 350 | D10: =(B10*C10)/10000000 -> 10.5
A11: 2027 | B11: 800000 | C11: 300 | D11: =(B11*C11)/10000000 -> 24
A12: 2028 | B12: 1500000 | C12: 275 | D12: =(B12*C12)/10000000 -> 41.25
A13: 2029 | B13: 2500000 | C13: 250 | D13: =(B13*C13)/10000000 -> 62.5
A15: Year | B15: Users | C15: Contribution/User | D15: Contribution Cr
A16: 2025 | B16: 100000 | C16: 255 | D16: =(B16*C16)/10000000 -> 2.55
A17: 2026 | B17: 300000 | C17: 255 | D17: =(B17*C17)/10000000 -> 7.65
A18: 2027 | B18: 800000 | C18: 255 | D18: =(B18*C18)/10000000 -> 20.4
A19: 2028 | B19: 1500000 | C19: 255 | D19: =(B19*C19)/10000000 -> 38.25
A20: 2029 | B20: 2500000 | C20: 255 | D20: =(B20*C20)/10000000 -> 63.75
A22: Metric | B22: Value
A23: Fixed Cost (₹ Cr) | B23: 20
A24: Contribution/User (₹) | B24: 255
A25: Breakeven Users | B25: =(B23*10000000)/B24 -> 784313.73
A27: Metric | B27: Value
A28: Year 3 Users | B28: 800000
A29: Breakeven Users | B29: 784314
A30: Status | B30: =IF(B28>B25,"Achieved","Not Achieved") -> Achieved
A35: Year 5 Users | B35: 2500000
A36: Year 5 Revenue (Cr) | B36: 175
A37: Year 5 Contribution (Cr) | B37: 63.75
A38: Breakeven Users | B38: 784314
A39: Breakeven Year | B39: Year 3

Sheet 13_Executive_Dashboard

Sheet 14_Launch_Priority_Matrix

Sheet 15_GTM_Recommendation
A2: BNPL TAM ($B) | B2: 8.1 | C2: =COUNTA('5_Competitors'!A2:A7) -> 6
A3: CAGR | B3: 0.28 | C3: =INDEX('5_Competitors'!A2:A7,MATCH(MAX('5_Competitors'!C2:C7),'5_Competitors'!C2:C7,0)) -> Bajaj Finance
A4: Top State | B4: Uttar Pradesh | C4: =INDEX('4_State_Data'!A:A,MATCH(MAX('4_State_Data'!B:B),'4_State_Data'!B:B,0)) -> Uttar Pradesh
A5: Market Leader | B5: Bajaj Finance | C5: =INDEX('5_Competitors'!A2:A7,MATCH(MAX('5_Competitors'!C2:C7),'5_Competitors'!C2:C7,0)) -> Bajaj Finance
A6: Competitor Users | B6: 154M | C6: =SUM('5_Competitors'!C2:C7) -> 165
A7: Revenue/User | B7: 700 | C7: =MAX('5_Competitors'!B:B) -> 0
A8: Contribution Margin | B8: 255 | C8: =SUM('5_Competitors'!B:B) -> 0
A9: Year 5 Revenue | B9: ₹175 Cr
A10: Recommendation | B10: ENTER
